AUTHORS
LICENSE
MANIFEST.in
README.rst
requirements_dev.txt
requirements_dev_python2.6.txt
setup.py
bugjar/__init__.py
bugjar/connection.py
bugjar/main.py
bugjar/net.py
bugjar/view.py
bugjar/widgets.py
bugjar.egg-info/PKG-INFO
bugjar.egg-info/SOURCES.txt
bugjar.egg-info/dependency_links.txt
bugjar.egg-info/entry_points.txt
bugjar.egg-info/requires.txt
bugjar.egg-info/top_level.txt
docs/Makefile
docs/conf.py
docs/headless.rst
docs/index.rst
docs/make.bat
docs/releases.rst
docs/internals/contributing.rst
docs/internals/roadmap.rst
tests/__init__.py