Metadata-Version: 1.1
Name: bugjar
Version: 0.1.0
Summary: A graphical Python debugger.
Home-page: http://pybee.org/bugjar
Author: Russell Keith-Magee
Author-email: russell@keith-magee.com
License: New BSD
Platform: UNKNOWN
Classifier: Development Status :: 3 - Alpha
Classifier: Intended Audience :: Developers
Classifier: License :: OSI Approved :: BSD License
Classifier: Operating System :: OS Independent
Classifier: Programming Language :: Python :: 2
Classifier: Topic :: Software Development
Classifier: Topic :: Utilities
